syntribos/__init__.py
syntribos/_i18n.py
syntribos/config.py
syntribos/constants.py
syntribos/issue.py
syntribos/result.py
syntribos/runner.py
syntribos/signal.py
syntribos/checks/__init__.py
syntribos/checks/content_validity.py
syntribos/checks/fingerprint.py
syntribos/checks/http.py
syntribos/checks/length.py
syntribos/checks/ssl.py
syntribos/checks/stacktrace.py
syntribos/checks/string.py
syntribos/checks/time.py
syntribos/checks/header/__init__.py
syntribos/checks/header/header.py
syntribos/checks/header/xst.py
syntribos/clients/__init__.py
syntribos/clients/http/__init__.py
syntribos/clients/http/base_http_client.py
syntribos/clients/http/client.py
syntribos/clients/http/debug_logger.py
syntribos/clients/http/parser.py
syntribos/extensions/__init__.py
syntribos/extensions/cinder/__init__.py
syntribos/extensions/cinder/client.py
syntribos/extensions/common_utils/__init__.py
syntribos/extensions/common_utils/client.py
syntribos/extensions/glance/__init__.py
syntribos/extensions/glance/client.py
syntribos/extensions/identity/__init__.py
syntribos/extensions/identity/client.py
syntribos/extensions/identity/models/__init__.py
syntribos/extensions/identity/models/base.py
syntribos/extensions/identity/models/v2.py
syntribos/extensions/identity/models/v3.py
syntribos/extensions/neutron/__init__.py
syntribos/extensions/neutron/client.py
syntribos/extensions/nova/__init__.py
syntribos/extensions/nova/client.py
syntribos/extensions/random_data/__init__.py
syntribos/extensions/random_data/client.py
syntribos/formatters/__init__.py
syntribos/formatters/json_formatter.py
syntribos/tests/__init__.py
syntribos/tests/base.py
syntribos/tests/auth/__init__.py
syntribos/tests/auth/auth.py
syntribos/tests/debug/__init__.py
syntribos/tests/debug/dry_run.py
syntribos/tests/fuzz/__init__.py
syntribos/tests/fuzz/base_fuzz.py
syntribos/tests/fuzz/buffer_overflow.py
syntribos/tests/fuzz/command_injection.py
syntribos-0.5.0.dist-info/DESCRIPTION.rst
syntribos-0.5.0.dist-info/METADATA
syntribos-0.5.0.dist-info/RECORD
syntribos-0.5.0.dist-info/WHEEL
syntribos-0.5.0.dist-info/entry_points.txt
syntribos-0.5.0.dist-info/metadata.json
syntribos-0.5.0.dist-info/pbr.json
syntribos-0.5.0.dist-info/top_level.txt
