Metadata-Version: 2.0
Name: syntribos
Version: 0.5.0
Summary: API Security Scanner
Home-page: https://docs.openstack.org/syntribos/latest/
Author: OpenStack Security Group
Author-email: openstack-dev@lists.openstack.org
License: Apache License, Version 2.0
Platform: UNKNOWN
Classifier: Environment :: Console
Classifier: Intended Audience :: Information Technology
Classifier: Intended Audience :: Developers
Classifier: License :: OSI Approved :: Apache Software License
Classifier: Natural Language :: English
Classifier: Operating System :: POSIX :: Linux
Classifier: Operating System :: MacOS :: MacOS X
Classifier: Programming Language :: Python
Classifier: Programming Language :: Python :: 2
Classifier: Programming Language :: Python :: 2.7
Classifier: Programming Language :: Python :: 3
Classifier: Programming Language :: Python :: 3.5
Classifier: Topic :: Security
Classifier: Topic :: Software Development :: Testing
Classifier: Topic :: Utilities
Requires-Dist: oslo.i18n (>=3.15.3)
Requires-Dist: six (>=1.9.0)
Requires-Dist: requests (>=2.14.2)
Requires-Dist: oslo.config (>=4.6.0)
Requires-Dist: oslo.utils (>=3.31.0)
Requires-Dist: python-cinderclient (>=3.2.0)
Requires-Dist: python-glanceclient (>=2.8.0)
Requires-Dist: python-neutronclient (>=6.3.0)
Requires-Dist: python-novaclient (>=9.1.0)
